gyb.py
linedirective.py
gyb-1.0.2.dist-info/DESCRIPTION.rst
gyb-1.0.2.dist-info/METADATA
gyb-1.0.2.dist-info/RECORD
gyb-1.0.2.dist-info/WHEEL
gyb-1.0.2.dist-info/entry_points.txt
gyb-1.0.2.dist-info/metadata.json
gyb-1.0.2.dist-info/top_level.txt
