Metadata-Version: 2.0
Name: gyb
Version: 1.0.2
Summary: Apple gyb, a simple python-based templating tool
Home-page: https://github.com/jph00/gyb
Author: Apple (pip packaged by Jeremy Howard)
Author-email: UNKNOWN
License: UNKNOWN
Keywords: development
Platform: UNKNOWN
Classifier: Development Status :: 5 - Production/Stable
Classifier: Intended Audience :: Developers
Classifier: Topic :: Software Development :: Build Tools
Classifier: License :: OSI Approved :: Apache Software License
Classifier: Programming Language :: Python :: 2
Classifier: Programming Language :: Python :: 2.7
Classifier: Programming Language :: Python :: 3
Classifier: Programming Language :: Python :: 3.4
Classifier: Programming Language :: Python :: 3.5
Classifier: Programming Language :: Python :: 3.6
Classifier: Programming Language :: Python :: 3.7
